{
    "id": "20260417_034708_c43bc1d2",
    "action": "refresh_best_all",
    "label": "Actualizar Mejores Marcas Usuarios",
    "status": "done",
    "created_at": "2026-04-17T03:47:08+02:00",
    "started_at": "2026-04-17T03:47:08+02:00",
    "finished_at": "2026-04-17T03:47:17+02:00",
    "exit_code": 0,
    "log_file": "C:\\Users\\Usuario\\Documents\\THC\\THC_Query\\logs\\tasks\\20260417_034708_c43bc1d2.log",
    "cancel_requested": false,
    "cancel_requested_at": null,
    "cancel_reason": null,
    "process_pid": null
}